[{"id": "efc5d5af-42cd-11ea-aeea-c8f750812c2f", "source_type": "web", "source_name": "university.which.co", "source_domain": "https://university.which.co.uk", "region": "uk", "type": "univerity", "display_name": "RNN Group", "name": "rnn_group", "number_of_dpt": 35, "geo_location": {"lat": 0, "lon": 0}, "address": "", "contact_no": ""}, {"id": "efc5d5af-42cd-11ea-aeea-c8f750812c2f", "source_type": "web", "source_name": "university.which.co", "source_domain": "https://university.which.co.uk", "region": "uk", "type": "univerity", "display_name": "RNN Group", "name": "rnn_group", "number_of_dpt": 35, "geo_location": {"lat": 0, "lon": 0}, "address": "", "contact_no": ""}, {"id": "efc5d5af-42cd-11ea-aeea-c8f750812c2f", "source_type": "web", "source_name": "university.which.co", "source_domain": "https://university.which.co.uk", "region": "uk", "type": "univerity", "display_name": "RNN Group", "name": "rnn_group", "number_of_dpt": 35, "geo_location": {"lat": 0, "lon": 0}, "address": "", "contact_no": ""}, {"id": "efc5d5af-42cd-11ea-aeea-c8f750812c2f", "source_type": "web", "source_name": "university.which.co", "source_domain": "https://university.which.co.uk", "region": "uk", "type": "univerity", "display_name": "RNN Group", "name": "rnn_group", "number_of_dpt": 35, "geo_location": {"lat": 0, "lon": 0}, "address": "", "contact_no": ""}, {"id": "efc5d5af-42cd-11ea-aeea-c8f750812c2f", "source_type": "web", "source_name": "university.which.co", "source_domain": "https://university.which.co.uk", "region": "uk", "type": "univerity", "display_name": "RNN Group", "name": "rnn_group", "number_of_dpt": 35, "geo_location": {"lat": 0, "lon": 0}, "address": "", "contact_no": ""}, {"id": "efc5d5af-42cd-11ea-aeea-c8f750812c2f", "source_type": "web", "source_name": "university.which.co", "source_domain": "https://university.which.co.uk", "region": "uk", "type": "univerity", "display_name": "RNN Group", "name": "rnn_group", "number_of_dpt": 35, "geo_location": {"lat": 0, "lon": 0}, "address": "", "contact_no": ""}, {"id": "efc5d5af-42cd-11ea-aeea-c8f750812c2f", "source_type": "web", "source_name": "university.which.co", "source_domain": "https://university.which.co.uk", "region": "uk", "type": "univerity", "display_name": "RNN Group", "name": "rnn_group", "number_of_dpt": 35, "geo_location": {"lat": 0, "lon": 0}, "address": "", "contact_no": ""}, {"id": "efc5d5af-42cd-11ea-aeea-c8f750812c2f", "source_type": "web", "source_name": "university.which.co", "source_domain": "https://university.which.co.uk", "region": "uk", "type": "univerity", "display_name": "RNN Group", "name": "rnn_group", "number_of_dpt": 35, "geo_location": {"lat": 0, "lon": 0}, "address": "", "contact_no": ""}, {"id": "efc5d5af-42cd-11ea-aeea-c8f750812c2f", "source_type": "web", "source_name": "university.which.co", "source_domain": "https://university.which.co.uk", "region": "uk", "type": "univerity", "display_name": "RNN Group", "name": "rnn_group", "number_of_dpt": 35, "geo_location": {"lat": 0, "lon": 0}, "address": "", "contact_no": ""}, {"id": "efc5d5af-42cd-11ea-aeea-c8f750812c2f", "source_type": "web", "source_name": "university.which.co", "source_domain": "https://university.which.co.uk", "region": "uk", "type": "univerity", "display_name": "RNN Group", "name": "rnn_group", "number_of_dpt": 35, "geo_location": {"lat": 0, "lon": 0}, "address": "", "contact_no": ""}, {"id": "efc5d5af-42cd-11ea-aeea-c8f750812c2f", "source_type": "web", "source_name": "university.which.co", "source_domain": "https://university.which.co.uk", "region": "uk", "type": "univerity", "display_name": "RNN Group", "name": "rnn_group", "number_of_dpt": 35, "geo_location": {"lat": 0, "lon": 0}, "address": "", "contact_no": ""}, {"id": "efc5d5af-42cd-11ea-aeea-c8f750812c2f", "source_type": "web", "source_name": "university.which.co", "source_domain": "https://university.which.co.uk", "region": "uk", "type": "univerity", "display_name": "RNN Group", "name": "rnn_group", "number_of_dpt": 35, "geo_location": {"lat": 0, "lon": 0}, "address": "", "contact_no": ""}, {"id": "efc5d5af-42cd-11ea-aeea-c8f750812c2f", "source_type": "web", "source_name": "university.which.co", "source_domain": "https://university.which.co.uk", "region": "uk", "type": "univerity", "display_name": "RNN Group", "name": "rnn_group", "number_of_dpt": 35, "geo_location": {"lat": 0, "lon": 0}, "address": "", "contact_no": ""}, {"id": "efc5d5af-42cd-11ea-aeea-c8f750812c2f", "source_type": "web", "source_name": "university.which.co", "source_domain": "https://university.which.co.uk", "region": "uk", "type": "univerity", "display_name": "RNN Group", "name": "rnn_group", "number_of_dpt": 35, "geo_location": {"lat": 0, "lon": 0}, "address": "", "contact_no": ""}, {"id": "efc5d5af-42cd-11ea-aeea-c8f750812c2f", "source_type": "web", "source_name": "university.which.co", "source_domain": "https://university.which.co.uk", "region": "uk", "type": "univerity", "display_name": "RNN Group", "name": "rnn_group", "number_of_dpt": 35, "geo_location": {"lat": 0, "lon": 0}, "address": "", "contact_no": ""}, {"id": "efc5d5af-42cd-11ea-aeea-c8f750812c2f", "source_type": "web", "source_name": "university.which.co", "source_domain": "https://university.which.co.uk", "region": "uk", "type": "univerity", "display_name": "RNN Group", "name": "rnn_group", "number_of_dpt": 35, "geo_location": {"lat": 0, "lon": 0}, "address": "", "contact_no": ""}, {"id": "efc5d5af-42cd-11ea-aeea-c8f750812c2f", "source_type": "web", "source_name": "university.which.co", "source_domain": "https://university.which.co.uk", "region": "uk", "type": "univerity", "display_name": "RNN Group", "name": "rnn_group", "number_of_dpt": 35, "geo_location": {"lat": 0, "lon": 0}, "address": "", "contact_no": ""}, {"id": "efc5d5af-42cd-11ea-aeea-c8f750812c2f", "source_type": "web", "source_name": "university.which.co", "source_domain": "https://university.which.co.uk", "region": "uk", "type": "univerity", "display_name": "RNN Group", "name": "rnn_group", "number_of_dpt": 35, "geo_location": {"lat": 0, "lon": 0}, "address": "", "contact_no": ""}, {"id": "efc5d5af-42cd-11ea-aeea-c8f750812c2f", "source_type": "web", "source_name": "university.which.co", "source_domain": "https://university.which.co.uk", "region": "uk", "type": "univerity", "display_name": "RNN Group", "name": "rnn_group", "number_of_dpt": 35, "geo_location": {"lat": 0, "lon": 0}, "address": "", "contact_no": ""}, {"id": "efc5d5af-42cd-11ea-aeea-c8f750812c2f", "source_type": "web", "source_name": "university.which.co", "source_domain": "https://university.which.co.uk", "region": "uk", "type": "univerity", "display_name": "RNN Group", "name": "rnn_group", "number_of_dpt": 35, "geo_location": {"lat": 0, "lon": 0}, "address": "", "contact_no": ""}, {"id": "efc5d5af-42cd-11ea-aeea-c8f750812c2f", "source_type": "web", "source_name": "university.which.co", "source_domain": "https://university.which.co.uk", "region": "uk", "type": "univerity", "display_name": "RNN Group", "name": "rnn_group", "number_of_dpt": 35, "geo_location": {"lat": 0, "lon": 0}, "address": "", "contact_no": ""}, {"id": "efc5d5af-42cd-11ea-aeea-c8f750812c2f", "source_type": "web", "source_name": "university.which.co", "source_domain": "https://university.which.co.uk", "region": "uk", "type": "univerity", "display_name": "RNN Group", "name": "rnn_group", "number_of_dpt": 35, "geo_location": {"lat": 0, "lon": 0}, "address": "", "contact_no": ""}, {"id": "efc5d5af-42cd-11ea-aeea-c8f750812c2f", "source_type": "web", "source_name": "university.which.co", "source_domain": "https://university.which.co.uk", "region": "uk", "type": "univerity", "display_name": "RNN Group", "name": "rnn_group", "number_of_dpt": 35, "geo_location": {"lat": 0, "lon": 0}, "address": "", "contact_no": ""}, {"id": "efc5d5af-42cd-11ea-aeea-c8f750812c2f", "source_type": "web", "source_name": "university.which.co", "source_domain": "https://university.which.co.uk", "region": "uk", "type": "univerity", "display_name": "RNN Group", "name": "rnn_group", "number_of_dpt": 35, "geo_location": {"lat": 0, "lon": 0}, "address": "", "contact_no": ""}, {"id": "efc5d5af-42cd-11ea-aeea-c8f750812c2f", "source_type": "web", "source_name": "university.which.co", "source_domain": "https://university.which.co.uk", "region": "uk", "type": "univerity", "display_name": "RNN Group", "name": "rnn_group", "number_of_dpt": 35, "geo_location": {"lat": 0, "lon": 0}, "address": "", "contact_no": ""}]